spkmc/__init__.py
spkmc/_version.py
spkmc/analysis/__init__.py
spkmc/analysis/ai_analyzer.py
spkmc/analysis/metrics.py
spkmc/analysis/prompts.py
spkmc/cli/__init__.py
spkmc/cli/__main__.py
spkmc/cli/commands.py
spkmc/cli/formatting.py
spkmc/cli/validators.py
spkmc/core/__init__.py
spkmc/core/distributions.py
spkmc/core/networks.py
spkmc/core/simulation.py
spkmc/core/transmissibility.py
spkmc/io/__init__.py
spkmc/io/experiments.py
spkmc/io/export.py
spkmc/io/results.py
spkmc/utils/__init__.py
spkmc/utils/gpu_utils.py
spkmc/utils/hardware.py
spkmc/utils/numba_utils.py
spkmc/utils/parallel.py
spkmc/visualization/__init__.py
spkmc/visualization/plots.py
spkmc-1.0.0.dist-info/licenses/LICENSE
spkmc-1.0.0.dist-info/METADATA
spkmc-1.0.0.dist-info/WHEEL
spkmc-1.0.0.dist-info/entry_points.txt
spkmc-1.0.0.dist-info/top_level.txt
spkmc-1.0.0.dist-info/RECORD
