Metadata-Version: 2.4
Name: spkmc
Version: 1.0.0
Summary: Shortest Path Kinetic Monte Carlo (SPKMC) for simulating epidemic spread on networks
Author: SPKMC Team
Author-email: SPKMC Team <example@example.com>
License: MIT
Classifier: Programming Language :: Python :: 3
Classifier: License :: OSI Approved :: MIT License
Classifier: Operating System :: OS Independent
Classifier: Topic :: Scientific/Engineering :: Mathematics
Classifier: Topic :: Scientific/Engineering :: Physics
Classifier: Topic :: Scientific/Engineering :: Information Analysis
Requires-Python: >=3.8
License-File: LICENSE
Requires-Dist: numpy>=1.20.0
Requires-Dist: scipy>=1.7.0
Requires-Dist: networkx>=2.6.0
Requires-Dist: matplotlib>=3.4.0
Requires-Dist: numba>=0.54.0
Requires-Dist: tqdm>=4.60.0
Requires-Dist: click>=8.0.0
Requires-Dist: pandas>=1.3.0
Requires-Dist: colorama>=0.4.4
Requires-Dist: rich>=10.0.0
Requires-Dist: openpyxl>=3.0.7
Requires-Dist: joblib>=1.0.1
Requires-Dist: questionary>=1.10.0
Requires-Dist: psutil>=5.8.0
Requires-Dist: openai>=1.0.0
Provides-Extra: dev
Requires-Dist: black>=21.5b2; extra == "dev"
Requires-Dist: isort>=5.9.0; extra == "dev"
Requires-Dist: mypy>=0.900; extra == "dev"
Requires-Dist: flake8>=3.9.0; extra == "dev"
Requires-Dist: flake8-bugbear>=23.0.0; extra == "dev"
Requires-Dist: pre-commit>=3.0.0; extra == "dev"
Requires-Dist: pytest>=6.0.0; extra == "dev"
Requires-Dist: pytest-cov>=2.12.1; extra == "dev"
Provides-Extra: gpu
Requires-Dist: cupy-cuda12x>=12.0.0; extra == "gpu"
Requires-Dist: cudf-cu12>=24.0.0; extra == "gpu"
Requires-Dist: cugraph-cu12>=24.0.0; extra == "gpu"
Dynamic: license-file
